{
  "parent": "minecraft:recipes/root",
  "criteria": {
    "has_raw": {
      "conditions": {
        "items": [
          {
            "items": "create_campanology:raw_musical_tin"
          }
        ]
      },
      "trigger": "minecraft:inventory_changed"
    },
    "has_the_recipe": {
      "conditions": {
        "recipe": "create_campanology:musical_tin_ingot_from_blasting_raw"
      },
      "trigger": "minecraft:recipe_unlocked"
    }
  },
  "requirements": [
    [
      "has_the_recipe",
      "has_raw"
    ]
  ],
  "rewards": {
    "recipes": [
      "create_campanology:musical_tin_ingot_from_blasting_raw"
    ]
  }
}